carehare/__init__.py
carehare/_channel.py
carehare/_channel_id_store.py
carehare/_connection.py
carehare/_consume_channel.py
carehare/_exceptions.py
carehare/_exchange_channel.py
carehare/_frame_writer.py
carehare/_heartbeat.py
carehare/_protocol.py
carehare/_rpc_channel.py
carehare-1.0.1.dist-info/LICENSE
carehare-1.0.1.dist-info/WHEEL
carehare-1.0.1.dist-info/METADATA
carehare-1.0.1.dist-info/RECORD
