Metadata-Version: 2.1
Name: carehare
Version: 1.0.1
Summary: asyncio RabbitMQ client
License: BSD
Author: Adam Hooper
Author-email: adam@adamhooper.com
Requires-Python: >=3.8,<4.0
Classifier: License :: Other/Proprietary License
Classifier: Programming Language :: Python :: 3
Classifier: Programming Language :: Python :: 3.8
Classifier: Programming Language :: Python :: 3.9
Requires-Dist: pamqp (>=3.0,<4.0)
